{
  "ID": "flg00",
  "Wall": {
    "UniqueID": 11915
  },
  "Floor": {
    "UniqueID": 5028
  },
  "Music": {
    "UniqueID": 4313
  },
  "FloorRotate": 0,
  "DIYWorkbench": {
    "UnitZ": 32,
    "UnitX": 26,
    "Layer": 0,
    "Item": {
      "BaseID": 4294971291,
      "ReFabric": 0,
      "ReBody": 1,
      "Rotation": 0,
      "Data4": 0,
      "UniqueID": 3995
    }
  },
  "DIYRangeHeight": 4,
  "DIYRangeWidth": 4,
  "DIYRangeLUZ": 32,
  "DIYRangeLUX": 26,
  "LifePoint": 28.2785416,
  "HobbyPoint": 9.496655,
  "FtrList": [
    {
      "UnitZ": 26,
      "UnitX": 36,
      "Layer": 0,
      "Item": {
        "BaseID": 4294970547,
        "ReFabric": 0,
        "ReBody": 1,
        "Rotation": 0,
        "Data4": 0,
        "UniqueID": 3251
      }
    },
    {
      "UnitZ": 26,
      "UnitX": 32,
      "Layer": 0,
      "Item": {
        "BaseID": 5790,
        "ReFabric": 0,
        "ReBody": 0,
        "Rotation": 0,
        "Data4": 0,
        "UniqueID": 5790
      }
    },
    {
      "UnitZ": 26,
      "UnitX": 26,
      "Layer": 0,
      "Item": {
        "BaseID": 12885102548,
        "ReFabric": 0,
        "ReBody": 3,
        "Rotation": 3,
        "Data4": 0,
        "UniqueID": 4052
      }
    },
    {
      "UnitZ": 36,
      "UnitX": 26,
      "Layer": 0,
      "Item": {
        "BaseID": 136862,
        "ReFabric": 0,
        "ReBody": 0,
        "Rotation": 2,
        "Data4": 0,
        "UniqueID": 5790
      }
    },
    {
      "UnitZ": 36,
      "UnitX": 34,
      "Layer": 0,
      "Item": {
        "BaseID": 132829,
        "ReFabric": 0,
        "ReBody": 0,
        "Rotation": 2,
        "Data4": 0,
        "UniqueID": 1757
      }
    },
    {
      "UnitZ": 25,
      "UnitX": 36,
      "Layer": 5,
      "Item": {
        "BaseID": 200625,
        "ReFabric": 0,
        "ReBody": 0,
        "Rotation": 3,
        "Data4": 0,
        "UniqueID": 4017
      }
    },
    {
      "UnitZ": 36,
      "UnitX": 28,
      "Layer": 0,
      "Item": {
        "BaseID": 141733924213,
        "ReFabric": 1,
        "ReBody": 1,
        "Rotation": 0,
        "Data4": 0,
        "UniqueID": 3445
      }
    },
    {
      "UnitZ": 32,
      "UnitX": 36,
      "Layer": 0,
      "Item": {
        "BaseID": 17179872867,
        "ReFabric": 0,
        "ReBody": 4,
        "Rotation": 0,
        "Data4": 0,
        "UniqueID": 3683
      }
    },
    {
      "UnitZ": 32,
      "UnitX": 34,
      "Layer": 0,
      "Item": {
        "BaseID": 12884907431,
        "ReFabric": 0,
        "ReBody": 3,
        "Rotation": 0,
        "Data4": 0,
        "UniqueID": 5543
      }
    },
    {
      "UnitZ": 32,
      "UnitX": 34,
      "Layer": 1,
      "Item": {
        "BaseID": 12884905936,
        "ReFabric": 0,
        "ReBody": 3,
        "Rotation": 0,
        "Data4": 0,
        "UniqueID": 4048
      }
    },
    {
      "UnitZ": 26,
      "UnitX": 30,
      "Layer": 0,
      "Item": {
        "BaseID": 12884905934,
        "ReFabric": 0,
        "ReBody": 3,
        "Rotation": 0,
        "Data4": 0,
        "UniqueID": 4046
      }
    },
    {
      "UnitZ": 26,
      "UnitX": 30,
      "Layer": 1,
      "Item": {
        "BaseID": 562954248392611,
        "ReFabric": 0,
        "ReBody": 1,
        "Rotation": 0,
        "Data4": 2,
        "UniqueID": 4003
      }
    },
    {
      "UnitZ": 32,
      "UnitX": 26,
      "Layer": 0,
      "Item": {
        "BaseID": 12884905942,
        "ReFabric": 0,
        "ReBody": 3,
        "Rotation": 0,
        "Data4": 0,
        "UniqueID": 4054
      }
    },
    {
      "UnitZ": 32,
      "UnitX": 26,
      "Layer": 1,
      "Item": {
        "BaseID": 7234,
        "ReFabric": 0,
        "ReBody": 0,
        "Rotation": 0,
        "Data4": 0,
        "UniqueID": 7234
      }
    },
    {
      "UnitZ": 26,
      "UnitX": 34,
      "Layer": 0,
      "Item": {
        "BaseID": 9766,
        "ReFabric": 0,
        "ReBody": 0,
        "Rotation": 0,
        "Data4": 0,
        "UniqueID": 9766
      }
    },
    {
      "UnitZ": 26,
      "UnitX": 34,
      "Layer": 1,
      "Item": {
        "BaseID": 3400,
        "ReFabric": 0,
        "ReBody": 0,
        "Rotation": 0,
        "Data4": 0,
        "UniqueID": 3400
      }
    },
    {
      "UnitZ": 23,
      "UnitX": 36,
      "Layer": 5,
      "Item": {
        "BaseID": 200638,
        "ReFabric": 0,
        "ReBody": 0,
        "Rotation": 3,
        "Data4": 0,
        "UniqueID": 4030
      }
    },
    {
      "UnitZ": 31,
      "UnitX": 36,
      "Layer": 0,
      "Item": {
        "BaseID": 429496734938,
        "ReFabric": 3,
        "ReBody": 4,
        "Rotation": 0,
        "Data4": 0,
        "UniqueID": 5338
      }
    },
    {
      "UnitZ": 31,
      "UnitX": 34,
      "Layer": 0,
      "Item": {
        "BaseID": 429496734938,
        "ReFabric": 3,
        "ReBody": 4,
        "Rotation": 0,
        "Data4": 0,
        "UniqueID": 5338
      }
    }
  ]
}